aditrace/__init__.py
aditrace/client.py
aditrace-0.1.0.dist-info/licenses/LICENSE
aditrace-0.1.0.dist-info/METADATA
aditrace-0.1.0.dist-info/WHEEL
aditrace-0.1.0.dist-info/top_level.txt
aditrace-0.1.0.dist-info/RECORD
