Metadata-Version: 2.4
Name: aditrace
Version: 0.1.0
Summary: A python client for Aditrace
Author: Giancarlo Garcia
License: MIT License
Project-URL: Homepage, https://github.com/giancarlogarcia/aditrace
Classifier: Programming Language :: Python :: 3
Classifier: License :: OSI Approved :: MIT License
Classifier: Operating System :: OS Independent
Requires-Python: >=3.7
License-File: LICENSE
Requires-Dist: cryptography
Requires-Dist: requests>=2.0.0
Dynamic: license-file
